manipy/__init__.py
manipy/config.py
manipy/core.py
manipy/inference.py
manipy/train_flow_model.py
manipy/train_rating_models.py
manipy/visualization.py
manipy/data/__init__.py
manipy/data/data_utils.py
manipy/data/dataset.py
manipy/data/dataset_generator.py
manipy/dist/polytope.py
manipy/dist/sampling.py
manipy/dist/test.py
manipy/metrics/__init__.py
manipy/metrics/oems.py
manipy/models/__init__.py
manipy/models/flow_models.py
manipy/models/layers.py
manipy/models/rating_models.py
manipy/optimal_transport/__init__.py
manipy/plot/flows.py
manipy/plot/test.py
manipy/scripts/__init__.py
manipy/scripts/generate_dataset.py
manipy/scripts/prepare_enviroment.py
manipy/stylegan/__init__.py
manipy/stylegan/core.py
manipy/stylegan/utils.py
manipy/utils/__init__.py
manipy/utils/_stylegan_utils.py
manipy/utils/appendix.py
manipy/utils/checkpoint_utils.py
manipy/utils/flow_utils.py
manipy/utils/general_utils.py
manipy/utils/logging_utils.py
manipy-0.1.8.dist-info/METADATA
manipy-0.1.8.dist-info/WHEEL
manipy-0.1.8.dist-info/top_level.txt
manipy-0.1.8.dist-info/RECORD
